unleash/__init__.py
unleash/arguments.py
unleash/parsing_base.py
unleash/parsing_cache.py
unleash/postprocess.py
unleash/data/__init__.py
unleash/data/data_loader.py
unleash/data/utils.py
unleash/evaluation/__init__.py
unleash/evaluation/settings.py
unleash/models/__init__.py
unleash/models/base.py
unleash/models/deberta.py
unleash/models/roberta.py
unleash/sampling/__init__.py
unleash/sampling/entropy_sampling.py
unleash/sampling/lilac_sampling.py
unleash/sampling/logppt_sampling.py
unleash/sampling/utils.py
unleash/tuning/__init__.py
unleash/tuning/early_stopping.py
unleash/tuning/trainer.py
unleash/tuning/utils.py
icse_unleash-1.0.0.dist-info/LICENSE
icse_unleash-1.0.0.dist-info/METADATA
icse_unleash-1.0.0.dist-info/WHEEL
icse_unleash-1.0.0.dist-info/top_level.txt
icse_unleash-1.0.0.dist-info/RECORD
