Metadata-Version: 2.2
Name: icse-unleash
Version: 1.0.0
Summary: UNLEASH: Semantic-based Log Parser with Pre-trained Language Models
Author-email: Hoang Le <levanhoang.psa@gmail.com>
License: MIT License
Project-URL: homepage, https://github.com/LogIntelligence/UNLEASH
Project-URL: issues, https://github.com/LogIntelligence/UNLEASH/issues
License-File: LICENSE
Requires-Dist: ipython
Requires-Dist: natsort
Requires-Dist: nltk
Requires-Dist: numpy
Requires-Dist: pandas
Requires-Dist: regex
Requires-Dist: scikit_learn
Requires-Dist: scipy
Requires-Dist: textdistance
Requires-Dist: torch
Requires-Dist: tqdm
Requires-Dist: transformers
Requires-Dist: datasets
Requires-Dist: pytest
